CHANGES.txt
LISENCE
MANIFEST.in
README.txt
setup.cfg
setup.py
rebecca/__init__.py
rebecca.fanstatic.egg-info/PKG-INFO
rebecca.fanstatic.egg-info/SOURCES.txt
rebecca.fanstatic.egg-info/dependency_links.txt
rebecca.fanstatic.egg-info/entry_points.txt
rebecca.fanstatic.egg-info/namespace_packages.txt
rebecca.fanstatic.egg-info/requires.txt
rebecca.fanstatic.egg-info/top_level.txt
rebecca/fanstatic/__init__.py
rebecca/fanstatic/apis.py
rebecca/fanstatic/commands.py
rebecca/fanstatic/directives.py
rebecca/fanstatic/interfaces.py
rebecca/fanstatic/subscribers.py
rebecca/fanstatic/tests/__init__.py
rebecca/fanstatic/tests/dummylibrary.py
rebecca/fanstatic/tests/integration_test.py
rebecca/fanstatic/tests/dummy_resources/dummy.css
rebecca/fanstatic/tests/dummy_resources/dummy1.js
rebecca/fanstatic/tests/dummy_resources/dummy2.js