Metadata-Version: 1.0
Name: rebecca.fanstatic
Version: 0.1.2
Summary: fanstatic utilities
Home-page: http://github.com/rebeccaframework/rebecca.fanstatic
Author: Atsushi Odagiri
Author-email: aodagx@gmail.com
License: MIT
Platform: UNKNOWN
